tvb/__init__.py
tvb/cli.py
tvb/command.py
tvb/config.py
tvb/device.py
tvb/dump_hprof.py
tvb/excel.py
tvb/info.py
tvb/info2.py
tvb/json_report.py
tvb/namespace.py
tvb/report.py
tvb/upload.py
alibaba_tvb-2.1.7.dist-info/LICENSE
alibaba_tvb-2.1.7.dist-info/METADATA
alibaba_tvb-2.1.7.dist-info/WHEEL
alibaba_tvb-2.1.7.dist-info/entry_points.txt
alibaba_tvb-2.1.7.dist-info/top_level.txt
alibaba_tvb-2.1.7.dist-info/RECORD
