Metadata-Version: 2.1
Name: alibaba-tvb
Version: 2.1.7
Summary: TV Bridge
Home-page: 
Author: Juncheng Chen
Author-email: juncheng.cjc@outlook.com
License: Apache 2.0
Keywords: android adb performence test tv
Classifier: Development Status :: 3 - Alpha
Classifier: Intended Audience :: Developers
Classifier: Topic :: Software Development :: Build Tools
Classifier: License :: OSI Approved :: Apache Software License
Classifier: Programming Language :: Python :: 3
Classifier: Programming Language :: Python :: 3.5
Classifier: Programming Language :: Python :: 3.7
Classifier: Programming Language :: Python :: 3.8
License-File: LICENSE
Requires-Dist: xlsxwriter
